{
  "updateTime": "2025-12-20T20:22:49.777Z",
  "updateTimeLocal": "2025/12/21 上午4:22:49",
  "currency": "TWD",
  "cryptos": [
    {
      "id": "bitcoin",
      "symbol": "BTC",
      "name": "Bitcoin",
      "icon": "₿",
      "price": 2780734,
      "priceUsd": 88277.26984126984,
      "change24h": 0.34618,
      "marketCap": 55492882059824,
      "volume24h": 608141627915,
      "high24h": 2787327,
      "low24h": 2767219
    },
    {
      "id": "ethereum",
      "symbol": "ETH",
      "name": "Ethereum",
      "icon": "Ξ",
      "price": 93903,
      "priceUsd": 2981.0476190476193,
      "change24h": -0.22226,
      "marketCap": 11326931976949,
      "volume24h": 259450475827,
      "high24h": 94443,
      "low24h": 93631
    },
    {
      "id": "binancecoin",
      "symbol": "BNB",
      "name": "BNB",
      "icon": "🔶",
      "price": 26884,
      "priceUsd": 853.4603174603175,
      "change24h": -0.61464,
      "marketCap": 3701620511647,
      "volume24h": 22829453933,
      "high24h": 27136,
      "low24h": 26818
    },
    {
      "id": "ripple",
      "symbol": "XRP",
      "name": "XRP",
      "icon": "✕",
      "price": 60.68,
      "priceUsd": 1.9263492063492063,
      "change24h": 0.73209,
      "marketCap": 3675463437851,
      "volume24h": 64197401322,
      "high24h": 61.57,
      "low24h": 59.75
    },
    {
      "id": "solana",
      "symbol": "SOL",
      "name": "Solana",
      "icon": "◎",
      "price": 3972.04,
      "priceUsd": 126.09650793650793,
      "change24h": -0.26249,
      "marketCap": 2232298525024,
      "volume24h": 67817618082,
      "high24h": 4007.43,
      "low24h": 3951.9
    },
    {
      "id": "dogecoin",
      "symbol": "DOGE",
      "name": "Dogecoin",
      "icon": "🐕",
      "price": 4.16,
      "priceUsd": 0.13206349206349208,
      "change24h": -0.72266,
      "marketCap": 699170167451,
      "volume24h": 17770498546,
      "high24h": 4.19,
      "low24h": 4.12
    },
    {
      "id": "cardano",
      "symbol": "ADA",
      "name": "Cardano",
      "icon": "₳",
      "price": 11.83,
      "priceUsd": 0.37555555555555553,
      "change24h": -0.86104,
      "marketCap": 433394601906,
      "volume24h": 10365254717,
      "high24h": 11.97,
      "low24h": 11.73
    },
    {
      "id": "chainlink",
      "symbol": "LINK",
      "name": "Chainlink",
      "icon": "⬡",
      "price": 396.31,
      "priceUsd": 12.581269841269842,
      "change24h": -0.20844,
      "marketCap": 280559542070,
      "volume24h": 8139667008,
      "high24h": 399.96,
      "low24h": 393.59
    },
    {
      "id": "avalanche-2",
      "symbol": "AVAX",
      "name": "Avalanche",
      "icon": "🔺",
      "price": 386.19,
      "priceUsd": 12.26,
      "change24h": -0.69036,
      "marketCap": 165826411718,
      "volume24h": 4992613965,
      "high24h": 389.42,
      "low24h": 383.69
    },
    {
      "id": "polkadot",
      "symbol": "DOT",
      "name": "Polkadot",
      "icon": "●",
      "price": 57.78,
      "priceUsd": 1.8342857142857143,
      "change24h": -1.97808,
      "marketCap": 95109678372,
      "volume24h": 2779645057,
      "high24h": 59.04,
      "low24h": 57.61
    }
  ]
}