{
  "updateTime": "2026-01-19T19:20:45.574Z",
  "updateTimeLocal": "2026/1/20 上午3:20:45",
  "currency": "TWD",
  "cryptos": [
    {
      "id": "bitcoin",
      "symbol": "BTC",
      "name": "Bitcoin",
      "icon": "₿",
      "price": 2936952,
      "priceUsd": 93236.57142857143,
      "change24h": -2.62904,
      "marketCap": 58660221064962,
      "volume24h": 1403880953572,
      "high24h": 3018683,
      "low24h": 2911020
    },
    {
      "id": "ethereum",
      "symbol": "ETH",
      "name": "Ethereum",
      "icon": "Ξ",
      "price": 101640,
      "priceUsd": 3226.6666666666665,
      "change24h": -4.17233,
      "marketCap": 12269162586986,
      "volume24h": 951459577976,
      "high24h": 106069,
      "low24h": 100686
    },
    {
      "id": "binancecoin",
      "symbol": "BNB",
      "name": "BNB",
      "icon": "🔶",
      "price": 29294,
      "priceUsd": 929.968253968254,
      "change24h": -2.55332,
      "marketCap": 3994567114197,
      "volume24h": 79245391330,
      "high24h": 30124,
      "low24h": 28823
    },
    {
      "id": "ripple",
      "symbol": "XRP",
      "name": "XRP",
      "icon": "✕",
      "price": 63.51,
      "priceUsd": 2.0161904761904763,
      "change24h": -2.46797,
      "marketCap": 3857436154320,
      "volume24h": 143638468189,
      "high24h": 65.16,
      "low24h": 61.03
    },
    {
      "id": "solana",
      "symbol": "SOL",
      "name": "Solana",
      "icon": "◎",
      "price": 4242.82,
      "priceUsd": 134.6926984126984,
      "change24h": -6.07401,
      "marketCap": 2396799300852,
      "volume24h": 183125368188,
      "high24h": 4517.75,
      "low24h": 4193.29
    },
    {
      "id": "dogecoin",
      "symbol": "DOGE",
      "name": "Dogecoin",
      "icon": "🐕",
      "price": 4.09,
      "priceUsd": 0.12984126984126984,
      "change24h": -6.02389,
      "marketCap": 687957168182,
      "volume24h": 64166185298,
      "high24h": 4.35,
      "low24h": 3.98
    },
    {
      "id": "cardano",
      "symbol": "ADA",
      "name": "Cardano",
      "icon": "₳",
      "price": 11.72,
      "priceUsd": 0.3720634920634921,
      "change24h": -5.94185,
      "marketCap": 430625885300,
      "volume24h": 31889347781,
      "high24h": 12.53,
      "low24h": 11.36
    },
    {
      "id": "chainlink",
      "symbol": "LINK",
      "name": "Chainlink",
      "icon": "⬡",
      "price": 408.13,
      "priceUsd": 12.956507936507936,
      "change24h": -6.69174,
      "marketCap": 288959484158,
      "volume24h": 20700257144,
      "high24h": 437.69,
      "low24h": 401.78
    },
    {
      "id": "avalanche-2",
      "symbol": "AVAX",
      "name": "Avalanche",
      "icon": "🔺",
      "price": 404.11,
      "priceUsd": 12.828888888888889,
      "change24h": -6.68133,
      "marketCap": 173829885248,
      "volume24h": 15174319456,
      "high24h": 434.41,
      "low24h": 395.64
    },
    {
      "id": "polkadot",
      "symbol": "DOT",
      "name": "Polkadot",
      "icon": "●",
      "price": 64.55,
      "priceUsd": 2.049206349206349,
      "change24h": -6.36407,
      "marketCap": 106424237560,
      "volume24h": 7998580527,
      "high24h": 69.27,
      "low24h": 61.21
    }
  ]
}