{
  "updateTime": "2025-12-31T11:20:28.438Z",
  "updateTimeLocal": "2025/12/31 下午7:20:28",
  "currency": "TWD",
  "cryptos": [
    {
      "id": "bitcoin",
      "symbol": "BTC",
      "name": "Bitcoin",
      "icon": "₿",
      "price": 2780815,
      "priceUsd": 88279.84126984127,
      "change24h": 1.10037,
      "marketCap": 55581899469047,
      "volume24h": 1189687655858,
      "high24h": 2790624,
      "low24h": 2744450
    },
    {
      "id": "ethereum",
      "symbol": "ETH",
      "name": "Ethereum",
      "icon": "Ξ",
      "price": 93483,
      "priceUsd": 2967.714285714286,
      "change24h": 0.39298,
      "marketCap": 11273581682469,
      "volume24h": 563960456998,
      "high24h": 93803,
      "low24h": 92304
    },
    {
      "id": "binancecoin",
      "symbol": "BNB",
      "name": "BNB",
      "icon": "🔶",
      "price": 27195,
      "priceUsd": 863.3333333333334,
      "change24h": 1.64706,
      "marketCap": 3744373452120,
      "volume24h": 41184659291,
      "high24h": 27231,
      "low24h": 26724
    },
    {
      "id": "ripple",
      "symbol": "XRP",
      "name": "XRP",
      "icon": "✕",
      "price": 58.68,
      "priceUsd": 1.8628571428571428,
      "change24h": 0.72705,
      "marketCap": 3557979047288,
      "volume24h": 51916287348,
      "high24h": 59.03,
      "low24h": 58.17
    },
    {
      "id": "solana",
      "symbol": "SOL",
      "name": "Solana",
      "icon": "◎",
      "price": 3955.62,
      "priceUsd": 125.57523809523809,
      "change24h": 1.59246,
      "marketCap": 2226282233806,
      "volume24h": 108895778549,
      "high24h": 3958.95,
      "low24h": 3863.15
    },
    {
      "id": "dogecoin",
      "symbol": "DOGE",
      "name": "Dogecoin",
      "icon": "🐕",
      "price": 3.86,
      "priceUsd": 0.12253968253968253,
      "change24h": -1.15095,
      "marketCap": 647931227163,
      "volume24h": 23091822132,
      "high24h": 3.9,
      "low24h": 3.83
    },
    {
      "id": "cardano",
      "symbol": "ADA",
      "name": "Cardano",
      "icon": "₳",
      "price": 10.99,
      "priceUsd": 0.3488888888888889,
      "change24h": -0.79467,
      "marketCap": 402374908695,
      "volume24h": 14294687045,
      "high24h": 11.11,
      "low24h": 10.9
    },
    {
      "id": "chainlink",
      "symbol": "LINK",
      "name": "Chainlink",
      "icon": "⬡",
      "price": 389.3,
      "priceUsd": 12.35873015873016,
      "change24h": -0.37186,
      "marketCap": 275318760845,
      "volume24h": 9482958390,
      "high24h": 392.65,
      "low24h": 385.66
    },
    {
      "id": "avalanche-2",
      "symbol": "AVAX",
      "name": "Avalanche",
      "icon": "🔺",
      "price": 392.67,
      "priceUsd": 12.465714285714286,
      "change24h": 0.5458,
      "marketCap": 168340561249,
      "volume24h": 7428815513,
      "high24h": 397.93,
      "low24h": 389.4
    },
    {
      "id": "polkadot",
      "symbol": "DOT",
      "name": "Polkadot",
      "icon": "●",
      "price": 56.88,
      "priceUsd": 1.8057142857142858,
      "change24h": -0.3076,
      "marketCap": 93619828746,
      "volume24h": 3208017260,
      "high24h": 57.58,
      "low24h": 56.37
    }
  ]
}