{
  "updateTime": "2026-01-31T18:35:46.290Z",
  "updateTimeLocal": "2026/2/1 上午2:35:46",
  "currency": "TWD",
  "cryptos": [
    {
      "id": "bitcoin",
      "symbol": "BTC",
      "name": "Bitcoin",
      "icon": "₿",
      "price": 2473422,
      "priceUsd": 78521.33333333333,
      "change24h": -4.7951,
      "marketCap": 49423067857725,
      "volume24h": 2132637397689,
      "high24h": 2663150,
      "low24h": 2471653
    },
    {
      "id": "ethereum",
      "symbol": "ETH",
      "name": "Ethereum",
      "icon": "Ξ",
      "price": 75423,
      "priceUsd": 2394.3809523809523,
      "change24h": -10.31331,
      "marketCap": 9144793803912,
      "volume24h": 1216558593945,
      "high24h": 86843,
      "low24h": 75366
    },
    {
      "id": "binancecoin",
      "symbol": "BNB",
      "name": "BNB",
      "icon": "🔶",
      "price": 24555,
      "priceUsd": 779.5238095238095,
      "change24h": -7.00413,
      "marketCap": 3355105703073,
      "volume24h": 72515054435,
      "high24h": 27151,
      "low24h": 24519
    },
    {
      "id": "ripple",
      "symbol": "XRP",
      "name": "XRP",
      "icon": "✕",
      "price": 49.54,
      "priceUsd": 1.5726984126984127,
      "change24h": -8.95152,
      "marketCap": 3016417044593,
      "volume24h": 156851554974,
      "high24h": 56.06,
      "low24h": 49.34
    },
    {
      "id": "solana",
      "symbol": "SOL",
      "name": "Solana",
      "icon": "◎",
      "price": 3254.32,
      "priceUsd": 103.31174603174604,
      "change24h": -10.59182,
      "marketCap": 1845478286222,
      "volume24h": 263332198035,
      "high24h": 3745.6,
      "low24h": 3249.36
    },
    {
      "id": "dogecoin",
      "symbol": "DOGE",
      "name": "Dogecoin",
      "icon": "🐕",
      "price": 3.21,
      "priceUsd": 0.1019047619047619,
      "change24h": -11.30259,
      "marketCap": 541988069805,
      "volume24h": 67472941493,
      "high24h": 3.73,
      "low24h": 3.21
    },
    {
      "id": "cardano",
      "symbol": "ADA",
      "name": "Cardano",
      "icon": "₳",
      "price": 8.99,
      "priceUsd": 0.2853968253968254,
      "change24h": -10.97577,
      "marketCap": 330938624213,
      "volume24h": 35916604866,
      "high24h": 10.44,
      "low24h": 8.95
    },
    {
      "id": "chainlink",
      "symbol": "LINK",
      "name": "Chainlink",
      "icon": "⬡",
      "price": 301.93,
      "priceUsd": 9.585079365079364,
      "change24h": -10.02762,
      "marketCap": 214125460901,
      "volume24h": 22768024841,
      "high24h": 345.58,
      "low24h": 301.86
    },
    {
      "id": "avalanche-2",
      "symbol": "AVAX",
      "name": "Avalanche",
      "icon": "🔺",
      "price": 307.86,
      "priceUsd": 9.773333333333333,
      "change24h": -9.19655,
      "marketCap": 133139079231,
      "volume24h": 17643110283,
      "high24h": 347.41,
      "low24h": 307.48
    },
    {
      "id": "polkadot",
      "symbol": "DOT",
      "name": "Polkadot",
      "icon": "●",
      "price": 47.06,
      "priceUsd": 1.493968253968254,
      "change24h": -10.77654,
      "marketCap": 78325715105,
      "volume24h": 6823824991,
      "high24h": 54.19,
      "low24h": 47.07
    }
  ]
}