{
  "updateTime": "2026-02-01T09:33:48.592Z",
  "updateTimeLocal": "2026/2/1 下午5:33:48",
  "currency": "TWD",
  "cryptos": [
    {
      "id": "bitcoin",
      "symbol": "BTC",
      "name": "Bitcoin",
      "icon": "₿",
      "price": 2486913,
      "priceUsd": 78949.61904761905,
      "change24h": -5.05078,
      "marketCap": 49634187924188,
      "volume24h": 2608335163212,
      "high24h": 2626612,
      "low24h": 2435652
    },
    {
      "id": "ethereum",
      "symbol": "ETH",
      "name": "Ethereum",
      "icon": "Ξ",
      "price": 76322,
      "priceUsd": 2422.9206349206347,
      "change24h": -8.37778,
      "marketCap": 9194672848973,
      "volume24h": 1625562364206,
      "high24h": 83782,
      "low24h": 74403
    },
    {
      "id": "binancecoin",
      "symbol": "BNB",
      "name": "BNB",
      "icon": "🔶",
      "price": 24580,
      "priceUsd": 780.3174603174604,
      "change24h": -7.29652,
      "marketCap": 3349739472462,
      "volume24h": 87215655610,
      "high24h": 26525,
      "low24h": 24214
    },
    {
      "id": "ripple",
      "symbol": "XRP",
      "name": "XRP",
      "icon": "✕",
      "price": 52.29,
      "priceUsd": 1.66,
      "change24h": -2.23552,
      "marketCap": 3180958105926,
      "volume24h": 201264702920,
      "high24h": 53.92,
      "low24h": 49.34
    },
    {
      "id": "solana",
      "symbol": "SOL",
      "name": "Solana",
      "icon": "◎",
      "price": 3319.12,
      "priceUsd": 105.36888888888889,
      "change24h": -9.04871,
      "marketCap": 1878776879514,
      "volume24h": 312174385721,
      "high24h": 3685.39,
      "low24h": 3180.42
    },
    {
      "id": "dogecoin",
      "symbol": "DOGE",
      "name": "Dogecoin",
      "icon": "🐕",
      "price": 3.33,
      "priceUsd": 0.10571428571428572,
      "change24h": -5.77953,
      "marketCap": 561954897203,
      "volume24h": 87193243987,
      "high24h": 3.54,
      "low24h": 3.17
    },
    {
      "id": "cardano",
      "symbol": "ADA",
      "name": "Cardano",
      "icon": "₳",
      "price": 9.34,
      "priceUsd": 0.2965079365079365,
      "change24h": -4.64764,
      "marketCap": 343459819532,
      "volume24h": 39201345063,
      "high24h": 9.86,
      "low24h": 8.86
    },
    {
      "id": "chainlink",
      "symbol": "LINK",
      "name": "Chainlink",
      "icon": "⬡",
      "price": 312.67,
      "priceUsd": 9.926031746031747,
      "change24h": -5.53833,
      "marketCap": 221342001119,
      "volume24h": 30329512274,
      "high24h": 333.03,
      "low24h": 296.72
    },
    {
      "id": "avalanche-2",
      "symbol": "AVAX",
      "name": "Avalanche",
      "icon": "🔺",
      "price": 320.23,
      "priceUsd": 10.166031746031747,
      "change24h": -4.01103,
      "marketCap": 138210363720,
      "volume24h": 21822792982,
      "high24h": 335.48,
      "low24h": 302.86
    },
    {
      "id": "polkadot",
      "symbol": "DOT",
      "name": "Polkadot",
      "icon": "●",
      "price": 48.54,
      "priceUsd": 1.5409523809523809,
      "change24h": -5.85556,
      "marketCap": 80600928234,
      "volume24h": 8303976266,
      "high24h": 51.94,
      "low24h": 46.34
    }
  ]
}