{
  "updateTime": "2025-12-23T14:23:34.877Z",
  "updateTimeLocal": "2025/12/23 下午10:23:34",
  "currency": "TWD",
  "cryptos": [
    {
      "id": "bitcoin",
      "symbol": "BTC",
      "name": "Bitcoin",
      "icon": "₿",
      "price": 2757548,
      "priceUsd": 87541.20634920635,
      "change24h": -2.72815,
      "marketCap": 55067593784016,
      "volume24h": 1463288961578,
      "high24h": 2837544,
      "low24h": 2742247
    },
    {
      "id": "ethereum",
      "symbol": "ETH",
      "name": "Ethereum",
      "icon": "Ξ",
      "price": 92510,
      "priceUsd": 2936.8253968253966,
      "change24h": -4.07928,
      "marketCap": 11186240881203,
      "volume24h": 648684919303,
      "high24h": 96563,
      "low24h": 92431
    },
    {
      "id": "binancecoin",
      "symbol": "BNB",
      "name": "BNB",
      "icon": "🔶",
      "price": 26667,
      "priceUsd": 846.5714285714286,
      "change24h": -2.36329,
      "marketCap": 3678579243608,
      "volume24h": 29980107360,
      "high24h": 27337,
      "low24h": 26672
    },
    {
      "id": "ripple",
      "symbol": "XRP",
      "name": "XRP",
      "icon": "✕",
      "price": 59.13,
      "priceUsd": 1.8771428571428572,
      "change24h": -3.11088,
      "marketCap": 3587446378160,
      "volume24h": 84333312078,
      "high24h": 61.22,
      "low24h": 59.05
    },
    {
      "id": "solana",
      "symbol": "SOL",
      "name": "Solana",
      "icon": "◎",
      "price": 3877.51,
      "priceUsd": 123.09555555555556,
      "change24h": -3.34181,
      "marketCap": 2184488793507,
      "volume24h": 116707794479,
      "high24h": 4034.47,
      "low24h": 3880.25
    },
    {
      "id": "dogecoin",
      "symbol": "DOGE",
      "name": "Dogecoin",
      "icon": "🐕",
      "price": 4.09,
      "priceUsd": 0.12984126984126984,
      "change24h": -2.85609,
      "marketCap": 686658558398,
      "volume24h": 31930493965,
      "high24h": 4.25,
      "low24h": 4.08
    },
    {
      "id": "cardano",
      "symbol": "ADA",
      "name": "Cardano",
      "icon": "₳",
      "price": 11.39,
      "priceUsd": 0.3615873015873016,
      "change24h": -3.80942,
      "marketCap": 417424046658,
      "volume24h": 16934130390,
      "high24h": 11.97,
      "low24h": 11.37
    },
    {
      "id": "chainlink",
      "symbol": "LINK",
      "name": "Chainlink",
      "icon": "⬡",
      "price": 384.18,
      "priceUsd": 12.196190476190477,
      "change24h": -4.46063,
      "marketCap": 272480962387,
      "volume24h": 15348517874,
      "high24h": 404.38,
      "low24h": 384.54
    },
    {
      "id": "avalanche-2",
      "symbol": "AVAX",
      "name": "Avalanche",
      "icon": "🔺",
      "price": 379.46,
      "priceUsd": 12.046349206349205,
      "change24h": -2.62028,
      "marketCap": 163198257496,
      "volume24h": 12133637054,
      "high24h": 394.39,
      "low24h": 379.64
    },
    {
      "id": "polkadot",
      "symbol": "DOT",
      "name": "Polkadot",
      "icon": "●",
      "price": 55.07,
      "priceUsd": 1.7482539682539682,
      "change24h": -4.8062,
      "marketCap": 90884757059,
      "volume24h": 5188155756,
      "high24h": 58.13,
      "low24h": 55.02
    }
  ]
}