{
  "updateTime": "2026-01-08T05:27:06.452Z",
  "updateTimeLocal": "2026/1/8 下午1:27:06",
  "currency": "TWD",
  "cryptos": [
    {
      "id": "bitcoin",
      "symbol": "BTC",
      "name": "Bitcoin",
      "icon": "₿",
      "price": 2875946,
      "priceUsd": 91299.87301587302,
      "change24h": -1.38206,
      "marketCap": 57477087426731,
      "volume24h": 1394282449402,
      "high24h": 2921902,
      "low24h": 2854390
    },
    {
      "id": "ethereum",
      "symbol": "ETH",
      "name": "Ethereum",
      "icon": "Ξ",
      "price": 99649,
      "priceUsd": 3163.4603174603176,
      "change24h": -2.71985,
      "marketCap": 12040369716493,
      "volume24h": 720429451444,
      "high24h": 102525,
      "low24h": 98511
    },
    {
      "id": "ripple",
      "symbol": "XRP",
      "name": "XRP",
      "icon": "✕",
      "price": 68.2,
      "priceUsd": 2.1650793650793654,
      "change24h": -3.88459,
      "marketCap": 4141483468325,
      "volume24h": 121152424300,
      "high24h": 71.82,
      "low24h": 67.73
    },
    {
      "id": "binancecoin",
      "symbol": "BNB",
      "name": "BNB",
      "icon": "🔶",
      "price": 28289,
      "priceUsd": 898.063492063492,
      "change24h": -1.49594,
      "marketCap": 3898482613492,
      "volume24h": 52521684420,
      "high24h": 28895,
      "low24h": 28095
    },
    {
      "id": "solana",
      "symbol": "SOL",
      "name": "Solana",
      "icon": "◎",
      "price": 4344.45,
      "priceUsd": 137.9190476190476,
      "change24h": -0.53718,
      "marketCap": 2454021708258,
      "volume24h": 141367955248,
      "high24h": 4388.36,
      "low24h": 4239.33
    },
    {
      "id": "dogecoin",
      "symbol": "DOGE",
      "name": "Dogecoin",
      "icon": "🐕",
      "price": 4.63,
      "priceUsd": 0.14698412698412697,
      "change24h": -0.22894,
      "marketCap": 779822979344,
      "volume24h": 46153192720,
      "high24h": 4.82,
      "low24h": 4.58
    },
    {
      "id": "cardano",
      "symbol": "ADA",
      "name": "Cardano",
      "icon": "₳",
      "price": 12.66,
      "priceUsd": 0.40190476190476193,
      "change24h": -2.12961,
      "marketCap": 464632331274,
      "volume24h": 18757307220,
      "high24h": 13.25,
      "low24h": 12.55
    },
    {
      "id": "chainlink",
      "symbol": "LINK",
      "name": "Chainlink",
      "icon": "⬡",
      "price": 424.93,
      "priceUsd": 13.48984126984127,
      "change24h": -1.75967,
      "marketCap": 300936090109,
      "volume24h": 15153645482,
      "high24h": 437.1,
      "low24h": 419.06
    },
    {
      "id": "avalanche-2",
      "symbol": "AVAX",
      "name": "Avalanche",
      "icon": "🔺",
      "price": 445.25,
      "priceUsd": 14.134920634920634,
      "change24h": -2.17257,
      "marketCap": 191658753119,
      "volume24h": 10776160102,
      "high24h": 456.64,
      "low24h": 438.84
    },
    {
      "id": "polkadot",
      "symbol": "DOT",
      "name": "Polkadot",
      "icon": "●",
      "price": 67.64,
      "priceUsd": 2.1473015873015875,
      "change24h": -2.45514,
      "marketCap": 111900633975,
      "volume24h": 4120549757,
      "high24h": 70.34,
      "low24h": 66.88
    }
  ]
}