{
  "updateTime": "2026-01-20T13:50:08.765Z",
  "updateTimeLocal": "2026/1/20 下午9:50:08",
  "currency": "TWD",
  "cryptos": [
    {
      "id": "bitcoin",
      "symbol": "BTC",
      "name": "Bitcoin",
      "icon": "₿",
      "price": 2877730,
      "priceUsd": 91356.50793650794,
      "change24h": -1.94543,
      "marketCap": 57504956315258,
      "volume24h": 1278407880267,
      "high24h": 2944150,
      "low24h": 2864686
    },
    {
      "id": "ethereum",
      "symbol": "ETH",
      "name": "Ethereum",
      "icon": "Ξ",
      "price": 97575,
      "priceUsd": 3097.6190476190477,
      "change24h": -3.86758,
      "marketCap": 11783184939770,
      "volume24h": 757961581781,
      "high24h": 101681,
      "low24h": 97518
    },
    {
      "id": "binancecoin",
      "symbol": "BNB",
      "name": "BNB",
      "icon": "🔶",
      "price": 28731,
      "priceUsd": 912.0952380952381,
      "change24h": -1.8208,
      "marketCap": 3917955026929,
      "volume24h": 61143687443,
      "high24h": 29447,
      "low24h": 28708
    },
    {
      "id": "ripple",
      "symbol": "XRP",
      "name": "XRP",
      "icon": "✕",
      "price": 60.8,
      "priceUsd": 1.93015873015873,
      "change24h": -2.19329,
      "marketCap": 3701704137543,
      "volume24h": 105634198298,
      "high24h": 63.81,
      "low24h": 60.74
    },
    {
      "id": "solana",
      "symbol": "SOL",
      "name": "Solana",
      "icon": "◎",
      "price": 4072.13,
      "priceUsd": 129.27396825396826,
      "change24h": -3.46239,
      "marketCap": 2303114103488,
      "volume24h": 140447799795,
      "high24h": 4255.58,
      "low24h": 4061.26
    },
    {
      "id": "dogecoin",
      "symbol": "DOGE",
      "name": "Dogecoin",
      "icon": "🐕",
      "price": 3.96,
      "priceUsd": 0.12571428571428572,
      "change24h": -1.97358,
      "marketCap": 667214919841,
      "volume24h": 32526003017,
      "high24h": 4.11,
      "low24h": 3.95
    },
    {
      "id": "cardano",
      "symbol": "ADA",
      "name": "Cardano",
      "icon": "₳",
      "price": 11.35,
      "priceUsd": 0.3603174603174603,
      "change24h": -1.86235,
      "marketCap": 417288680613,
      "volume24h": 17952757414,
      "high24h": 11.74,
      "low24h": 11.28
    },
    {
      "id": "chainlink",
      "symbol": "LINK",
      "name": "Chainlink",
      "icon": "⬡",
      "price": 394.99,
      "priceUsd": 12.53936507936508,
      "change24h": -1.88454,
      "marketCap": 279705447487,
      "volume24h": 10443440948,
      "high24h": 409.78,
      "low24h": 394.61
    },
    {
      "id": "avalanche-2",
      "symbol": "AVAX",
      "name": "Avalanche",
      "icon": "🔺",
      "price": 391.63,
      "priceUsd": 12.432698412698413,
      "change24h": -2.40166,
      "marketCap": 168875950729,
      "volume24h": 9781878480,
      "high24h": 404.58,
      "low24h": 391.4
    },
    {
      "id": "polkadot",
      "symbol": "DOT",
      "name": "Polkadot",
      "icon": "●",
      "price": 61.76,
      "priceUsd": 1.9606349206349205,
      "change24h": -0.87887,
      "marketCap": 102507160957,
      "volume24h": 5339233965,
      "high24h": 64.86,
      "low24h": 61.76
    }
  ]
}