{
  "updateTime": "2026-01-25T05:29:43.230Z",
  "updateTimeLocal": "2026/1/25 下午1:29:43",
  "currency": "TWD",
  "cryptos": [
    {
      "id": "bitcoin",
      "symbol": "BTC",
      "name": "Bitcoin",
      "icon": "₿",
      "price": 2788747,
      "priceUsd": 88531.6507936508,
      "change24h": -0.96314,
      "marketCap": 55723020906059,
      "volume24h": 527823161139,
      "high24h": 2815868,
      "low24h": 2785162
    },
    {
      "id": "ethereum",
      "symbol": "ETH",
      "name": "Ethereum",
      "icon": "Ξ",
      "price": 92348,
      "priceUsd": 2931.6825396825398,
      "change24h": -0.62655,
      "marketCap": 11144865516256,
      "volume24h": 253842529933,
      "high24h": 93001,
      "low24h": 92115
    },
    {
      "id": "binancecoin",
      "symbol": "BNB",
      "name": "BNB",
      "icon": "🔶",
      "price": 27642,
      "priceUsd": 877.5238095238095,
      "change24h": -1.25275,
      "marketCap": 3767341832514,
      "volume24h": 19432202040,
      "high24h": 28007,
      "low24h": 27582
    },
    {
      "id": "ripple",
      "symbol": "XRP",
      "name": "XRP",
      "icon": "✕",
      "price": 59.53,
      "priceUsd": 1.8898412698412699,
      "change24h": -1.21973,
      "marketCap": 3623713084555,
      "volume24h": 31780591630,
      "high24h": 60.28,
      "low24h": 59.51
    },
    {
      "id": "solana",
      "symbol": "SOL",
      "name": "Solana",
      "icon": "◎",
      "price": 3970.88,
      "priceUsd": 126.05968253968254,
      "change24h": -0.88684,
      "marketCap": 2246986518630,
      "volume24h": 53795961894,
      "high24h": 4006.41,
      "low24h": 3965.29
    },
    {
      "id": "dogecoin",
      "symbol": "DOGE",
      "name": "Dogecoin",
      "icon": "🐕",
      "price": 3.87,
      "priceUsd": 0.12285714285714286,
      "change24h": -0.89118,
      "marketCap": 650883702591,
      "volume24h": 11710821107,
      "high24h": 3.91,
      "low24h": 3.86
    },
    {
      "id": "cardano",
      "symbol": "ADA",
      "name": "Cardano",
      "icon": "₳",
      "price": 11.19,
      "priceUsd": 0.35523809523809524,
      "change24h": -1.17154,
      "marketCap": 411351088605,
      "volume24h": 6085667599,
      "high24h": 11.32,
      "low24h": 11.12
    },
    {
      "id": "chainlink",
      "symbol": "LINK",
      "name": "Chainlink",
      "icon": "⬡",
      "price": 379.49,
      "priceUsd": 12.047301587301588,
      "change24h": -1.06983,
      "marketCap": 268687491046,
      "volume24h": 4734050145,
      "high24h": 383.88,
      "low24h": 378.78
    },
    {
      "id": "avalanche-2",
      "symbol": "AVAX",
      "name": "Avalanche",
      "icon": "🔺",
      "price": 375.06,
      "priceUsd": 11.906666666666666,
      "change24h": -1.57204,
      "marketCap": 161746373868,
      "volume24h": 4104419338,
      "high24h": 381.06,
      "low24h": 373.42
    },
    {
      "id": "polkadot",
      "symbol": "DOT",
      "name": "Polkadot",
      "icon": "●",
      "price": 59.69,
      "priceUsd": 1.894920634920635,
      "change24h": -1.43431,
      "marketCap": 99042962543,
      "volume24h": 1931715356,
      "high24h": 60.7,
      "low24h": 59.64
    }
  ]
}