{
  "updateTime": "2025-12-19T03:25:37.754Z",
  "updateTimeLocal": "2025/12/19 上午11:25:37",
  "currency": "TWD",
  "cryptos": [
    {
      "id": "bitcoin",
      "symbol": "BTC",
      "name": "Bitcoin",
      "icon": "₿",
      "price": 2726509,
      "priceUsd": 86555.84126984127,
      "change24h": 0.02211,
      "marketCap": 54241811252494,
      "volume24h": 1900860087756,
      "high24h": 2811227,
      "low24h": 2669086
    },
    {
      "id": "ethereum",
      "symbol": "ETH",
      "name": "Ethereum",
      "icon": "Ξ",
      "price": 90507,
      "priceUsd": 2873.2380952380954,
      "change24h": 1.43892,
      "marketCap": 10867811751309,
      "volume24h": 1012085811415,
      "high24h": 94196,
      "low24h": 87789
    },
    {
      "id": "binancecoin",
      "symbol": "BNB",
      "name": "BNB",
      "icon": "🔶",
      "price": 26270,
      "priceUsd": 833.968253968254,
      "change24h": -1.17325,
      "marketCap": 3605952112654,
      "volume24h": 93494045418,
      "high24h": 26810,
      "low24h": 25883
    },
    {
      "id": "ripple",
      "symbol": "XRP",
      "name": "XRP",
      "icon": "✕",
      "price": 57.38,
      "priceUsd": 1.8215873015873016,
      "change24h": -2.06905,
      "marketCap": 3461568290102,
      "volume24h": 130907981556,
      "high24h": 60.81,
      "low24h": 55.93
    },
    {
      "id": "solana",
      "symbol": "SOL",
      "name": "Solana",
      "icon": "◎",
      "price": 3796.09,
      "priceUsd": 120.51079365079366,
      "change24h": -2.46269,
      "marketCap": 2130970853616,
      "volume24h": 214135918022,
      "high24h": 4051.22,
      "low24h": 3711
    },
    {
      "id": "dogecoin",
      "symbol": "DOGE",
      "name": "Dogecoin",
      "icon": "🐕",
      "price": 3.9,
      "priceUsd": 0.1238095238095238,
      "change24h": -1.74531,
      "marketCap": 590862953896,
      "volume24h": 58198158983,
      "high24h": 4.11,
      "low24h": 3.8
    },
    {
      "id": "cardano",
      "symbol": "ADA",
      "name": "Cardano",
      "icon": "₳",
      "price": 11.2,
      "priceUsd": 0.3555555555555555,
      "change24h": -2.86249,
      "marketCap": 409412633165,
      "volume24h": 25069789051,
      "high24h": 11.88,
      "low24h": 10.95
    },
    {
      "id": "chainlink",
      "symbol": "LINK",
      "name": "Chainlink",
      "icon": "⬡",
      "price": 381.16,
      "priceUsd": 12.100317460317461,
      "change24h": -0.79277,
      "marketCap": 265100894113,
      "volume24h": 23516889817,
      "high24h": 403.01,
      "low24h": 371.76
    },
    {
      "id": "avalanche-2",
      "symbol": "AVAX",
      "name": "Avalanche",
      "icon": "🔺",
      "price": 364.86,
      "priceUsd": 11.582857142857144,
      "change24h": -1.45123,
      "marketCap": 156485471224,
      "volume24h": 15685667871,
      "high24h": 386.77,
      "low24h": 355.73
    },
    {
      "id": "polkadot",
      "symbol": "DOT",
      "name": "Polkadot",
      "icon": "●",
      "price": 55.74,
      "priceUsd": 1.7695238095238095,
      "change24h": -1.61084,
      "marketCap": 91673958469,
      "volume24h": 7335048569,
      "high24h": 59.25,
      "low24h": 54.57
    }
  ]
}