{
  "updateTime": "2026-01-18T19:17:39.639Z",
  "updateTimeLocal": "2026/1/19 上午3:17:39",
  "currency": "TWD",
  "cryptos": [
    {
      "id": "bitcoin",
      "symbol": "BTC",
      "name": "Bitcoin",
      "icon": "₿",
      "price": 3017002,
      "priceUsd": 95777.84126984127,
      "change24h": 0.06876,
      "marketCap": 60277377706100,
      "volume24h": 601921257743,
      "high24h": 3018826,
      "low24h": 3000049
    },
    {
      "id": "ethereum",
      "symbol": "ETH",
      "name": "Ethereum",
      "icon": "Ξ",
      "price": 106054,
      "priceUsd": 3366.7936507936506,
      "change24h": 1.17675,
      "marketCap": 12818895255411,
      "volume24h": 405280471496,
      "high24h": 106388,
      "low24h": 104242
    },
    {
      "id": "binancecoin",
      "symbol": "BNB",
      "name": "BNB",
      "icon": "🔶",
      "price": 30064,
      "priceUsd": 954.4126984126984,
      "change24h": -0.19317,
      "marketCap": 4101463682669,
      "volume24h": 36163518509,
      "high24h": 30141,
      "low24h": 29831
    },
    {
      "id": "ripple",
      "symbol": "XRP",
      "name": "XRP",
      "icon": "✕",
      "price": 65.11,
      "priceUsd": 2.066984126984127,
      "change24h": -0.8005,
      "marketCap": 3962220869528,
      "volume24h": 42642396485,
      "high24h": 65.64,
      "low24h": 64.71
    },
    {
      "id": "solana",
      "symbol": "SOL",
      "name": "Solana",
      "icon": "◎",
      "price": 4518.94,
      "priceUsd": 143.45841269841267,
      "change24h": -0.89422,
      "marketCap": 2555460486728,
      "volume24h": 79917064156,
      "high24h": 4568.34,
      "low24h": 4483.36
    },
    {
      "id": "dogecoin",
      "symbol": "DOGE",
      "name": "Dogecoin",
      "icon": "🐕",
      "price": 4.35,
      "priceUsd": 0.13809523809523808,
      "change24h": -0.78217,
      "marketCap": 732743665064,
      "volume24h": 17307499258,
      "high24h": 4.39,
      "low24h": 4.32
    },
    {
      "id": "cardano",
      "symbol": "ADA",
      "name": "Cardano",
      "icon": "₳",
      "price": 12.47,
      "priceUsd": 0.3958730158730159,
      "change24h": -1.52244,
      "marketCap": 459121949341,
      "volume24h": 10495003023,
      "high24h": 12.69,
      "low24h": 12.36
    },
    {
      "id": "chainlink",
      "symbol": "LINK",
      "name": "Chainlink",
      "icon": "⬡",
      "price": 437.42,
      "priceUsd": 13.886349206349207,
      "change24h": 0.30706,
      "marketCap": 309983903912,
      "volume24h": 7879427513,
      "high24h": 438.22,
      "low24h": 431.46
    },
    {
      "id": "avalanche-2",
      "symbol": "AVAX",
      "name": "Avalanche",
      "icon": "🔺",
      "price": 433.02,
      "priceUsd": 13.746666666666666,
      "change24h": -0.93581,
      "marketCap": 186619051209,
      "volume24h": 5881733141,
      "high24h": 437.81,
      "low24h": 427.06
    },
    {
      "id": "polkadot",
      "symbol": "DOT",
      "name": "Polkadot",
      "icon": "●",
      "price": 68.99,
      "priceUsd": 2.19015873015873,
      "change24h": -1.27096,
      "marketCap": 114289887645,
      "volume24h": 3540105633,
      "high24h": 69.87,
      "low24h": 67.59
    }
  ]
}