{
  "updateTime": "2026-01-04T05:27:32.975Z",
  "updateTimeLocal": "2026/1/4 下午1:27:32",
  "currency": "TWD",
  "cryptos": [
    {
      "id": "bitcoin",
      "symbol": "BTC",
      "name": "Bitcoin",
      "icon": "₿",
      "price": 2868202,
      "priceUsd": 91054.03174603175,
      "change24h": 1.57962,
      "marketCap": 57277922758835,
      "volume24h": 837112955549,
      "high24h": 2869501,
      "low24h": 2804853
    },
    {
      "id": "ethereum",
      "symbol": "ETH",
      "name": "Ethereum",
      "icon": "Ξ",
      "price": 98770,
      "priceUsd": 3135.5555555555557,
      "change24h": 1.14822,
      "marketCap": 11922985154604,
      "volume24h": 399793450022,
      "high24h": 99116,
      "low24h": 96659
    },
    {
      "id": "ripple",
      "symbol": "XRP",
      "name": "XRP",
      "icon": "✕",
      "price": 64.95,
      "priceUsd": 2.061904761904762,
      "change24h": 1.30578,
      "marketCap": 3938018705939,
      "volume24h": 85436324304,
      "high24h": 64.9,
      "low24h": 62.47
    },
    {
      "id": "binancecoin",
      "symbol": "BNB",
      "name": "BNB",
      "icon": "🔶",
      "price": 27845,
      "priceUsd": 883.968253968254,
      "change24h": 1.21039,
      "marketCap": 3835441434647,
      "volume24h": 29177485049,
      "high24h": 27892,
      "low24h": 27263
    },
    {
      "id": "solana",
      "symbol": "SOL",
      "name": "Solana",
      "icon": "◎",
      "price": 4218.27,
      "priceUsd": 133.91333333333336,
      "change24h": 1.69035,
      "marketCap": 2375951027289,
      "volume24h": 91262251507,
      "high24h": 4225.25,
      "low24h": 4078.85
    },
    {
      "id": "dogecoin",
      "symbol": "DOGE",
      "name": "Dogecoin",
      "icon": "🐕",
      "price": 4.78,
      "priceUsd": 0.15174603174603177,
      "change24h": 6.56505,
      "marketCap": 803532126253,
      "volume24h": 64178681647,
      "high24h": 4.79,
      "low24h": 4.38
    },
    {
      "id": "cardano",
      "symbol": "ADA",
      "name": "Cardano",
      "icon": "₳",
      "price": 12.45,
      "priceUsd": 0.3952380952380952,
      "change24h": 0.43856,
      "marketCap": 456291445696,
      "volume24h": 18069027611,
      "high24h": 12.58,
      "low24h": 12.04
    },
    {
      "id": "chainlink",
      "symbol": "LINK",
      "name": "Chainlink",
      "icon": "⬡",
      "price": 420.07,
      "priceUsd": 13.335555555555555,
      "change24h": 1.43346,
      "marketCap": 297369365979,
      "volume24h": 10706064844,
      "high24h": 420.39,
      "low24h": 408.01
    },
    {
      "id": "avalanche-2",
      "symbol": "AVAX",
      "name": "Avalanche",
      "icon": "🔺",
      "price": 438.91,
      "priceUsd": 13.933650793650795,
      "change24h": -0.61877,
      "marketCap": 188821192616,
      "volume24h": 9990805894,
      "high24h": 448.55,
      "low24h": 430.29
    },
    {
      "id": "polkadot",
      "symbol": "DOT",
      "name": "Polkadot",
      "icon": "●",
      "price": 67.08,
      "priceUsd": 2.1295238095238096,
      "change24h": -0.40639,
      "marketCap": 110810935331,
      "volume24h": 4158447382,
      "high24h": 67.64,
      "low24h": 66.26
    }
  ]
}