{
  "updateTime": "2026-01-07T03:40:51.842Z",
  "updateTimeLocal": "2026/1/7 上午11:40:51",
  "currency": "TWD",
  "cryptos": [
    {
      "id": "bitcoin",
      "symbol": "BTC",
      "name": "Bitcoin",
      "icon": "₿",
      "price": 2919465,
      "priceUsd": 92681.42857142857,
      "change24h": -1.11701,
      "marketCap": 58309104039176,
      "volume24h": 1743937108298,
      "high24h": 2969002,
      "low24h": 2879821
    },
    {
      "id": "ethereum",
      "symbol": "ETH",
      "name": "Ethereum",
      "icon": "Ξ",
      "price": 102808,
      "priceUsd": 3263.746031746032,
      "change24h": 1.25829,
      "marketCap": 12408393508137,
      "volume24h": 891470253379,
      "high24h": 103837,
      "low24h": 100563
    },
    {
      "id": "ripple",
      "symbol": "XRP",
      "name": "XRP",
      "icon": "✕",
      "price": 71.25,
      "priceUsd": 2.261904761904762,
      "change24h": -5.19622,
      "marketCap": 4324563032994,
      "volume24h": 216909594953,
      "high24h": 75.51,
      "low24h": 69.75
    },
    {
      "id": "binancecoin",
      "symbol": "BNB",
      "name": "BNB",
      "icon": "🔶",
      "price": 28630,
      "priceUsd": 908.8888888888889,
      "change24h": 0.24715,
      "marketCap": 3943271778684,
      "volume24h": 52732861629,
      "high24h": 29012,
      "low24h": 28141
    },
    {
      "id": "solana",
      "symbol": "SOL",
      "name": "Solana",
      "icon": "◎",
      "price": 4394.65,
      "priceUsd": 139.5126984126984,
      "change24h": 0.93294,
      "marketCap": 2482566876747,
      "volume24h": 204683715183,
      "high24h": 4497.71,
      "low24h": 4300.95
    },
    {
      "id": "dogecoin",
      "symbol": "DOGE",
      "name": "Dogecoin",
      "icon": "🐕",
      "price": 4.68,
      "priceUsd": 0.14857142857142855,
      "change24h": -2.24674,
      "marketCap": 787122911094,
      "volume24h": 65429138144,
      "high24h": 4.89,
      "low24h": 4.54
    },
    {
      "id": "cardano",
      "symbol": "ADA",
      "name": "Cardano",
      "icon": "₳",
      "price": 12.97,
      "priceUsd": 0.41174603174603175,
      "change24h": -3.33427,
      "marketCap": 475751014251,
      "volume24h": 26791282581,
      "high24h": 13.71,
      "low24h": 12.69
    },
    {
      "id": "chainlink",
      "symbol": "LINK",
      "name": "Chainlink",
      "icon": "⬡",
      "price": 434.98,
      "priceUsd": 13.80888888888889,
      "change24h": -0.0921,
      "marketCap": 308006965082,
      "volume24h": 22772916136,
      "high24h": 446.36,
      "low24h": 425.63
    },
    {
      "id": "avalanche-2",
      "symbol": "AVAX",
      "name": "Avalanche",
      "icon": "🔺",
      "price": 455.44,
      "priceUsd": 14.458412698412697,
      "change24h": 0.19559,
      "marketCap": 196068654189,
      "volume24h": 15062378008,
      "high24h": 465.42,
      "low24h": 448.89
    },
    {
      "id": "polkadot",
      "symbol": "DOT",
      "name": "Polkadot",
      "icon": "●",
      "price": 68.84,
      "priceUsd": 2.1853968253968254,
      "change24h": -1.56931,
      "marketCap": 113920996793,
      "volume24h": 7148302590,
      "high24h": 71,
      "low24h": 66.91
    }
  ]
}