{
  "updateTime": "2025-12-28T23:21:29.744Z",
  "updateTimeLocal": "2025/12/29 上午7:21:29",
  "currency": "TWD",
  "cryptos": [
    {
      "id": "bitcoin",
      "symbol": "BTC",
      "name": "Bitcoin",
      "icon": "₿",
      "price": 2754244,
      "priceUsd": 87436.31746031746,
      "change24h": 0.13048,
      "marketCap": 54970354760306,
      "volume24h": 544560316286,
      "high24h": 2760961,
      "low24h": 2744512
    },
    {
      "id": "ethereum",
      "symbol": "ETH",
      "name": "Ethereum",
      "icon": "Ξ",
      "price": 92444,
      "priceUsd": 2934.7301587301586,
      "change24h": 0.31246,
      "marketCap": 11147734131154,
      "volume24h": 297904477765,
      "high24h": 92803,
      "low24h": 91893
    },
    {
      "id": "binancecoin",
      "symbol": "BNB",
      "name": "BNB",
      "icon": "🔶",
      "price": 26951,
      "priceUsd": 855.5873015873016,
      "change24h": 1.88742,
      "marketCap": 3710134662522,
      "volume24h": 28196851481,
      "high24h": 27175,
      "low24h": 26360
    },
    {
      "id": "ripple",
      "symbol": "XRP",
      "name": "XRP",
      "icon": "✕",
      "price": 58.49,
      "priceUsd": 1.856825396825397,
      "change24h": 0.03305,
      "marketCap": 3547909096411,
      "volume24h": 33368974160,
      "high24h": 58.93,
      "low24h": 58.2
    },
    {
      "id": "solana",
      "symbol": "SOL",
      "name": "Solana",
      "icon": "◎",
      "price": 3897.38,
      "priceUsd": 123.72634920634921,
      "change24h": -0.05279,
      "marketCap": 2193178910800,
      "volume24h": 67543889819,
      "high24h": 3918.07,
      "low24h": 3864.91
    },
    {
      "id": "dogecoin",
      "symbol": "DOGE",
      "name": "Dogecoin",
      "icon": "🐕",
      "price": 3.88,
      "priceUsd": 0.12317460317460317,
      "change24h": -0.0647,
      "marketCap": 652222569563,
      "volume24h": 15494985096,
      "high24h": 3.92,
      "low24h": 3.86
    },
    {
      "id": "cardano",
      "symbol": "ADA",
      "name": "Cardano",
      "icon": "₳",
      "price": 11.45,
      "priceUsd": 0.3634920634920635,
      "change24h": -0.30924,
      "marketCap": 419429025187,
      "volume24h": 14924912348,
      "high24h": 11.76,
      "low24h": 11.37
    },
    {
      "id": "chainlink",
      "symbol": "LINK",
      "name": "Chainlink",
      "icon": "⬡",
      "price": 390.18,
      "priceUsd": 12.386666666666667,
      "change24h": 0.13673,
      "marketCap": 276314097282,
      "volume24h": 8292114476,
      "high24h": 394.1,
      "low24h": 387.13
    },
    {
      "id": "avalanche-2",
      "symbol": "AVAX",
      "name": "Avalanche",
      "icon": "🔺",
      "price": 395.47,
      "priceUsd": 12.554603174603175,
      "change24h": -0.02335,
      "marketCap": 170084597629,
      "volume24h": 7171940862,
      "high24h": 403.11,
      "low24h": 393.4
    },
    {
      "id": "polkadot",
      "symbol": "DOT",
      "name": "Polkadot",
      "icon": "●",
      "price": 57.85,
      "priceUsd": 1.8365079365079366,
      "change24h": -3.2098,
      "marketCap": 95437970197,
      "volume24h": 4146069109,
      "high24h": 60.06,
      "low24h": 57.59
    }
  ]
}