{
  "updateTime": "2025-12-25T13:33:12.122Z",
  "updateTimeLocal": "2025/12/25 下午9:33:12",
  "currency": "TWD",
  "cryptos": [
    {
      "id": "bitcoin",
      "symbol": "BTC",
      "name": "Bitcoin",
      "icon": "₿",
      "price": 2749327,
      "priceUsd": 87280.22222222222,
      "change24h": 0.50217,
      "marketCap": 54887550936774,
      "volume24h": 749092157188,
      "high24h": 2765285,
      "low24h": 2721793
    },
    {
      "id": "ethereum",
      "symbol": "ETH",
      "name": "Ethereum",
      "icon": "Ξ",
      "price": 91895,
      "priceUsd": 2917.3015873015875,
      "change24h": -0.011,
      "marketCap": 11089459432300,
      "volume24h": 396518990558,
      "high24h": 93019,
      "low24h": 91336
    },
    {
      "id": "binancecoin",
      "symbol": "BNB",
      "name": "BNB",
      "icon": "🔶",
      "price": 26271,
      "priceUsd": 834,
      "change24h": -0.26877,
      "marketCap": 3617980281859,
      "volume24h": 22394069309,
      "high24h": 26709,
      "low24h": 26266
    },
    {
      "id": "ripple",
      "symbol": "XRP",
      "name": "XRP",
      "icon": "✕",
      "price": 58.6,
      "priceUsd": 1.8603174603174604,
      "change24h": -0.13221,
      "marketCap": 3550172526152,
      "volume24h": 48865944134,
      "high24h": 59.02,
      "low24h": 58.22
    },
    {
      "id": "solana",
      "symbol": "SOL",
      "name": "Solana",
      "icon": "◎",
      "price": 3830.55,
      "priceUsd": 121.60476190476192,
      "change24h": -0.22552,
      "marketCap": 2154386699121,
      "volume24h": 64995428968,
      "high24h": 3873.87,
      "low24h": 3814.17
    },
    {
      "id": "dogecoin",
      "symbol": "DOGE",
      "name": "Dogecoin",
      "icon": "🐕",
      "price": 3.97,
      "priceUsd": 0.12603174603174605,
      "change24h": -1.38236,
      "marketCap": 603902632372,
      "volume24h": 17942802327,
      "high24h": 4.06,
      "low24h": 3.96
    },
    {
      "id": "cardano",
      "symbol": "ADA",
      "name": "Cardano",
      "icon": "₳",
      "price": 11.02,
      "priceUsd": 0.34984126984126984,
      "change24h": -1.96123,
      "marketCap": 403894049344,
      "volume24h": 12418860436,
      "high24h": 11.35,
      "low24h": 11.01
    },
    {
      "id": "chainlink",
      "symbol": "LINK",
      "name": "Chainlink",
      "icon": "⬡",
      "price": 383.68,
      "priceUsd": 12.180317460317461,
      "change24h": 0.20362,
      "marketCap": 271754853852,
      "volume24h": 8221741710,
      "high24h": 388.44,
      "low24h": 379.58
    },
    {
      "id": "avalanche-2",
      "symbol": "AVAX",
      "name": "Avalanche",
      "icon": "🔺",
      "price": 383.61,
      "priceUsd": 12.178095238095239,
      "change24h": 1.17874,
      "marketCap": 164848075521,
      "volume24h": 7330120757,
      "high24h": 386.34,
      "low24h": 374.66
    },
    {
      "id": "polkadot",
      "symbol": "DOT",
      "name": "Polkadot",
      "icon": "●",
      "price": 54.04,
      "priceUsd": 1.7155555555555555,
      "change24h": -0.68469,
      "marketCap": 89105053601,
      "volume24h": 3010982071,
      "high24h": 55.03,
      "low24h": 53.63
    }
  ]
}