{
  "updateTime": "2025-12-24T15:23:54.875Z",
  "updateTimeLocal": "2025/12/24 下午11:23:54",
  "currency": "TWD",
  "cryptos": [
    {
      "id": "bitcoin",
      "symbol": "BTC",
      "name": "Bitcoin",
      "icon": "₿",
      "price": 2724762,
      "priceUsd": 86500.38095238095,
      "change24h": -0.68305,
      "marketCap": 54490372211277,
      "volume24h": 1104065820383,
      "high24h": 2770379,
      "low24h": 2721106
    },
    {
      "id": "ethereum",
      "symbol": "ETH",
      "name": "Ethereum",
      "icon": "Ξ",
      "price": 91322,
      "priceUsd": 2899.1111111111113,
      "change24h": -0.61795,
      "marketCap": 11046634045855,
      "volume24h": 586613396751,
      "high24h": 93815,
      "low24h": 91336
    },
    {
      "id": "binancecoin",
      "symbol": "BNB",
      "name": "BNB",
      "icon": "🔶",
      "price": 26313,
      "priceUsd": 835.3333333333334,
      "change24h": -0.79488,
      "marketCap": 3628868875310,
      "volume24h": 28759956226,
      "high24h": 26698,
      "low24h": 26205
    },
    {
      "id": "ripple",
      "symbol": "XRP",
      "name": "XRP",
      "icon": "✕",
      "price": 58.34,
      "priceUsd": 1.8520634920634922,
      "change24h": -1.55208,
      "marketCap": 3536168088887,
      "volume24h": 61828913710,
      "high24h": 59.44,
      "low24h": 57.78
    },
    {
      "id": "solana",
      "symbol": "SOL",
      "name": "Solana",
      "icon": "◎",
      "price": 3822.98,
      "priceUsd": 121.36444444444444,
      "change24h": -1.28835,
      "marketCap": 2150730846333,
      "volume24h": 96547670321,
      "high24h": 3932.02,
      "low24h": 3798.33
    },
    {
      "id": "dogecoin",
      "symbol": "DOGE",
      "name": "Dogecoin",
      "icon": "🐕",
      "price": 4,
      "priceUsd": 0.12698412698412698,
      "change24h": -1.73152,
      "marketCap": 672177808863,
      "volume24h": 23698301856,
      "high24h": 4.11,
      "low24h": 3.98
    },
    {
      "id": "cardano",
      "symbol": "ADA",
      "name": "Cardano",
      "icon": "₳",
      "price": 11.11,
      "priceUsd": 0.3526984126984127,
      "change24h": -2.29056,
      "marketCap": 407663010795,
      "volume24h": 13958993742,
      "high24h": 11.47,
      "low24h": 11.11
    },
    {
      "id": "chainlink",
      "symbol": "LINK",
      "name": "Chainlink",
      "icon": "⬡",
      "price": 379.53,
      "priceUsd": 12.048571428571428,
      "change24h": -1.54324,
      "marketCap": 268844881512,
      "volume24h": 10913752527,
      "high24h": 392.03,
      "low24h": 379.58
    },
    {
      "id": "avalanche-2",
      "symbol": "AVAX",
      "name": "Avalanche",
      "icon": "🔺",
      "price": 375.18,
      "priceUsd": 11.91047619047619,
      "change24h": -0.2588,
      "marketCap": 161171512213,
      "volume24h": 8002537591,
      "high24h": 386.28,
      "low24h": 375.44
    },
    {
      "id": "polkadot",
      "symbol": "DOT",
      "name": "Polkadot",
      "icon": "●",
      "price": 54.03,
      "priceUsd": 1.7152380952380952,
      "change24h": -1.62331,
      "marketCap": 89087263820,
      "volume24h": 3855542235,
      "high24h": 55.91,
      "low24h": 54.04
    }
  ]
}