{
  "updateTime": "2026-01-22T22:26:11.162Z",
  "updateTimeLocal": "2026/1/23 上午6:26:11",
  "currency": "TWD",
  "cryptos": [
    {
      "id": "bitcoin",
      "symbol": "BTC",
      "name": "Bitcoin",
      "icon": "₿",
      "price": 2823215,
      "priceUsd": 89625.87301587302,
      "change24h": -0.71273,
      "marketCap": 56380194584389,
      "volume24h": 1283872838188,
      "high24h": 2855327,
      "low24h": 2799274
    },
    {
      "id": "ethereum",
      "symbol": "ETH",
      "name": "Ethereum",
      "icon": "Ξ",
      "price": 93210,
      "priceUsd": 2959.0476190476193,
      "change24h": -2.3345,
      "marketCap": 11230625906934,
      "volume24h": 728373087688,
      "high24h": 95949,
      "low24h": 91972
    },
    {
      "id": "binancecoin",
      "symbol": "BNB",
      "name": "BNB",
      "icon": "🔶",
      "price": 28093,
      "priceUsd": 891.8412698412699,
      "change24h": -0.09628,
      "marketCap": 3828173891219,
      "volume24h": 39088448593,
      "high24h": 28350,
      "low24h": 27777
    },
    {
      "id": "ripple",
      "symbol": "XRP",
      "name": "XRP",
      "icon": "✕",
      "price": 60.9,
      "priceUsd": 1.9333333333333333,
      "change24h": -2.65916,
      "marketCap": 3698176775564,
      "volume24h": 81927127432,
      "high24h": 62.56,
      "low24h": 60.27
    },
    {
      "id": "solana",
      "symbol": "SOL",
      "name": "Solana",
      "icon": "◎",
      "price": 4054.67,
      "priceUsd": 128.71968253968254,
      "change24h": -2.14793,
      "marketCap": 2293697241234,
      "volume24h": 112463972713,
      "high24h": 4143.68,
      "low24h": 4016.95
    },
    {
      "id": "dogecoin",
      "symbol": "DOGE",
      "name": "Dogecoin",
      "icon": "🐕",
      "price": 3.92,
      "priceUsd": 0.12444444444444444,
      "change24h": -3.05936,
      "marketCap": 659496429161,
      "volume24h": 25755193491,
      "high24h": 4.04,
      "low24h": 3.91
    },
    {
      "id": "cardano",
      "symbol": "ADA",
      "name": "Cardano",
      "icon": "₳",
      "price": 11.36,
      "priceUsd": 0.36063492063492064,
      "change24h": -3.06605,
      "marketCap": 417357447392,
      "volume24h": 12873502257,
      "high24h": 11.72,
      "low24h": 11.27
    },
    {
      "id": "chainlink",
      "symbol": "LINK",
      "name": "Chainlink",
      "icon": "⬡",
      "price": 387.16,
      "priceUsd": 12.29079365079365,
      "change24h": -2.58153,
      "marketCap": 273864068851,
      "volume24h": 10779659864,
      "high24h": 397.74,
      "low24h": 384.4
    },
    {
      "id": "avalanche-2",
      "symbol": "AVAX",
      "name": "Avalanche",
      "icon": "🔺",
      "price": 384.35,
      "priceUsd": 12.201587301587303,
      "change24h": -3.35804,
      "marketCap": 165732705556,
      "volume24h": 7679793476,
      "high24h": 398.66,
      "low24h": 382.03
    },
    {
      "id": "polkadot",
      "symbol": "DOT",
      "name": "Polkadot",
      "icon": "●",
      "price": 60.96,
      "priceUsd": 1.9352380952380952,
      "change24h": -2.71081,
      "marketCap": 101069748933,
      "volume24h": 2978685167,
      "high24h": 62.66,
      "low24h": 60.5
    }
  ]
}