{
  "updateTime": "2025-12-25T07:23:49.084Z",
  "updateTimeLocal": "2025/12/25 下午3:23:49",
  "currency": "TWD",
  "cryptos": [
    {
      "id": "bitcoin",
      "symbol": "BTC",
      "name": "Bitcoin",
      "icon": "₿",
      "price": 2758786,
      "priceUsd": 87580.50793650794,
      "change24h": 0.93132,
      "marketCap": 55090829750466,
      "volume24h": 782016242702,
      "high24h": 2765285,
      "low24h": 2721106
    },
    {
      "id": "ethereum",
      "symbol": "ETH",
      "name": "Ethereum",
      "icon": "Ξ",
      "price": 92404,
      "priceUsd": 2933.4603174603176,
      "change24h": 0.24287,
      "marketCap": 11160231638536,
      "volume24h": 380378797910,
      "high24h": 93019,
      "low24h": 91336
    },
    {
      "id": "binancecoin",
      "symbol": "BNB",
      "name": "BNB",
      "icon": "🔶",
      "price": 26482,
      "priceUsd": 840.6984126984127,
      "change24h": 0.40943,
      "marketCap": 3647510412935,
      "volume24h": 23156386962,
      "high24h": 26709,
      "low24h": 26205
    },
    {
      "id": "ripple",
      "symbol": "XRP",
      "name": "XRP",
      "icon": "✕",
      "price": 58.9,
      "priceUsd": 1.8698412698412699,
      "change24h": 1.19927,
      "marketCap": 3567085477860,
      "volume24h": 48320185724,
      "high24h": 58.95,
      "low24h": 58.19
    },
    {
      "id": "solana",
      "symbol": "SOL",
      "name": "Solana",
      "icon": "◎",
      "price": 3838.97,
      "priceUsd": 121.87206349206349,
      "change24h": 0.52356,
      "marketCap": 2162597447615,
      "volume24h": 68187077160,
      "high24h": 3873.87,
      "low24h": 3808.54
    },
    {
      "id": "dogecoin",
      "symbol": "DOGE",
      "name": "Dogecoin",
      "icon": "🐕",
      "price": 4.02,
      "priceUsd": 0.1276190476190476,
      "change24h": 0.50616,
      "marketCap": 676697125625,
      "volume24h": 16290931688,
      "high24h": 4.06,
      "low24h": 3.98
    },
    {
      "id": "cardano",
      "symbol": "ADA",
      "name": "Cardano",
      "icon": "₳",
      "price": 11.29,
      "priceUsd": 0.3584126984126984,
      "change24h": 0.71397,
      "marketCap": 413909296781,
      "volume24h": 11136005322,
      "high24h": 11.35,
      "low24h": 11.11
    },
    {
      "id": "chainlink",
      "symbol": "LINK",
      "name": "Chainlink",
      "icon": "⬡",
      "price": 386.39,
      "priceUsd": 12.266349206349206,
      "change24h": 0.90402,
      "marketCap": 273614817272,
      "volume24h": 8653683001,
      "high24h": 388.44,
      "low24h": 379.58
    },
    {
      "id": "avalanche-2",
      "symbol": "AVAX",
      "name": "Avalanche",
      "icon": "🔺",
      "price": 383.13,
      "priceUsd": 12.162857142857142,
      "change24h": 1.72707,
      "marketCap": 164636581214,
      "volume24h": 6784828354,
      "high24h": 383.56,
      "low24h": 374.66
    },
    {
      "id": "polkadot",
      "symbol": "DOT",
      "name": "Polkadot",
      "icon": "●",
      "price": 54.61,
      "priceUsd": 1.7336507936507937,
      "change24h": 0.57776,
      "marketCap": 90145502985,
      "volume24h": 2923900384,
      "high24h": 55.03,
      "low24h": 53.98
    }
  ]
}